src/__init__.py
src/alpha_miner.py
tests/__init__.py
tests/test_alpha_miner.py
alpha_miner-0.1.3.dist-info/LICENSE
alpha_miner-0.1.3.dist-info/METADATA
alpha_miner-0.1.3.dist-info/WHEEL
alpha_miner-0.1.3.dist-info/top_level.txt
alpha_miner-0.1.3.dist-info/RECORD
