Metadata-Version: 2.2
Name: alpha-miner
Version: 0.1.3
Summary: The alpha-miner package implements the α-algorithm for process mining, transforming event logs into petri nets.
Home-page: https://github.com/felix-reichel/alpha-miner
Author: Felix Reichel
Author-email: kontakt@felixreichel.com
Classifier: Programming Language :: Python :: 3
Classifier: License :: OSI Approved :: MIT License
Classifier: Operating System :: OS Independent
Requires-Python: >=3.6
License-File: LICENSE
Dynamic: author
Dynamic: author-email
Dynamic: classifier
Dynamic: description
Dynamic: description-content-type
Dynamic: home-page
Dynamic: requires-python
Dynamic: summary
